timesheet/__init__.py
timesheet/cli.py
timesheet/configuration.py
timesheet/models.py
timesheet/commands/__init__.py
timesheet/commands/abort.py
timesheet/commands/active.py
timesheet/commands/base.py
timesheet/commands/completers.py
timesheet/commands/daily_detail.py
timesheet/commands/daily_report.py
timesheet/commands/delete.py
timesheet/commands/edit_last.py
timesheet/commands/end.py
timesheet/commands/export.py
timesheet/commands/full_report.py
timesheet/commands/help.py
timesheet/commands/import_.py
timesheet/commands/rename.py
timesheet/commands/start.py
timesheet/commands/subjects.py
timesheet/commands/version.py
timesheet-0.9.7.dist-info/DESCRIPTION.rst
timesheet-0.9.7.dist-info/METADATA
timesheet-0.9.7.dist-info/RECORD
timesheet-0.9.7.dist-info/WHEEL
timesheet-0.9.7.dist-info/dependency_links.txt
timesheet-0.9.7.dist-info/entry_points.txt
timesheet-0.9.7.dist-info/metadata.json
timesheet-0.9.7.dist-info/top_level.txt
