Metadata-Version: 2.0
Name: timesheet
Version: 0.9.7
Summary: Simple timesheet tracking system
Home-page: http://github.com/pylover/timesheet
Author: Vahid Mardani
Author-email: vahid.mardani@gmail.com
License: UNKNOWN
Platform: any
Classifier: Development Status :: 4 - Beta
Classifier: License :: Freeware
Classifier: Intended Audience :: Developers
Classifier: Operating System :: OS Independent
Classifier: Programming Language :: Python :: 2.6
Classifier: Programming Language :: Python :: 2.7
Classifier: Programming Language :: Python :: 3.3
Classifier: Programming Language :: Python :: 3.4
Classifier: Programming Language :: Python :: 3.5
Requires-Dist: PrettyTable
Requires-Dist: appdirs (>=1.3.0)
Requires-Dist: argcomplete
Requires-Dist: pymlconf (>=0.3.10)
Requires-Dist: sqlalchemy
